pymkm/__init__.py
pymkm/biology/__init__.py
pymkm/biology/oxygen_effect.py
pymkm/data/__init__.py
pymkm/data/elements.json
pymkm/data/defaults/__init__.py
pymkm/data/defaults/fluka_2020_0/Z01_A01_Hydrogen.txt
pymkm/data/defaults/fluka_2020_0/Z02_A04_Helium.txt
pymkm/data/defaults/fluka_2020_0/Z03_A07_Lithium.txt
pymkm/data/defaults/fluka_2020_0/Z04_A09_Beryllium.txt
pymkm/data/defaults/fluka_2020_0/Z05_A10_Boron.txt
pymkm/data/defaults/fluka_2020_0/Z06_A12_Carbon.txt
pymkm/data/defaults/fluka_2020_0/Z07_A14_Nitrogen.txt
pymkm/data/defaults/fluka_2020_0/Z08_A16_Oxygen.txt
pymkm/data/defaults/fluka_2020_0/Z09_A19_Fluorine.txt
pymkm/data/defaults/fluka_2020_0/Z10_A20_Neon.txt
pymkm/data/defaults/fluka_2020_0/__init__.py
pymkm/data/defaults/geant4_11_3_0/Z01_A01_Hydrogen.txt
pymkm/data/defaults/geant4_11_3_0/Z02_A04_Helium.txt
pymkm/data/defaults/geant4_11_3_0/Z03_A07_Lithium.txt
pymkm/data/defaults/geant4_11_3_0/Z04_A09_Beryllium.txt
pymkm/data/defaults/geant4_11_3_0/Z05_A10_Boron.txt
pymkm/data/defaults/geant4_11_3_0/Z06_A12_Carbon.txt
pymkm/data/defaults/geant4_11_3_0/Z07_A14_Nitrogen.txt
pymkm/data/defaults/geant4_11_3_0/Z08_A16_Oxygen.txt
pymkm/data/defaults/geant4_11_3_0/Z09_A19_Fluorine.txt
pymkm/data/defaults/geant4_11_3_0/Z10_A20_Neon.txt
pymkm/data/defaults/geant4_11_3_0/__init__.py
pymkm/data/defaults/mstar_3_12/Z01_A01_Hydrogen.txt
pymkm/data/defaults/mstar_3_12/Z02_A04_Helium.txt
pymkm/data/defaults/mstar_3_12/Z03_A07_Lithium.txt
pymkm/data/defaults/mstar_3_12/Z04_A09_Beryllium.txt
pymkm/data/defaults/mstar_3_12/Z05_A10_Boron.txt
pymkm/data/defaults/mstar_3_12/Z06_A12_Carbon.txt
pymkm/data/defaults/mstar_3_12/Z07_A14_Nitrogen.txt
pymkm/data/defaults/mstar_3_12/Z08_A16_Oxygen.txt
pymkm/data/defaults/mstar_3_12/Z09_A19_Fluorine.txt
pymkm/data/defaults/mstar_3_12/Z10_A20_Neon.txt
pymkm/data/defaults/mstar_3_12/__init__.py
pymkm/io/__init__.py
pymkm/io/data_registry.py
pymkm/io/stopping_power.py
pymkm/io/table_set.py
pymkm/mktable/__init__.py
pymkm-1.0.0.dist-info/licenses/LICENSE
pymkm-1.0.0.dist-info/METADATA
pymkm-1.0.0.dist-info/WHEEL
pymkm-1.0.0.dist-info/top_level.txt
pymkm-1.0.0.dist-info/RECORD
