Metadata-Version: 2.4
Name: pymkm
Version: 1.0.0
Summary: Microdosimetric Kinetic Model utilities for radiobiology research and hadrontherapy.
Author-email: Giuseppe Magro <giuseppe.magro@cnao.it>
License: MIT
Project-URL: Homepage, https://github.com/BeppeMagro/pymkm
Project-URL: Repository, https://github.com/BeppeMagro/pymkm
Project-URL: Issues, https://github.com/BeppeMagro/pymkm/issues
Keywords: MKM,RBE,radiobiology,hadrontherapy,LET
Classifier: Programming Language :: Python :: 3
Classifier: License :: OSI Approved :: MIT License
Classifier: Operating System :: OS Independent
Requires-Python: >=3.9
License-File: LICENSE
Requires-Dist: matplotlib
Requires-Dist: numpy
Requires-Dist: pandas
Requires-Dist: scipy
Requires-Dist: tabulate
Requires-Dist: tqdm
Provides-Extra: dev
Requires-Dist: pytest; extra == "dev"
Requires-Dist: pytest-cov; extra == "dev"
Requires-Dist: black; extra == "dev"
Requires-Dist: mypy; extra == "dev"
Dynamic: license-file
